setup.py
authorizenet/__init__.py
authorizenet/apicontractsv1.py
authorizenet/apicontrollers.py
authorizenet/apicontrollersbase.py
authorizenet/constants.py
authorizenet_sdk_python.egg-info/PKG-INFO
authorizenet_sdk_python.egg-info/SOURCES.txt
authorizenet_sdk_python.egg-info/dependency_links.txt
authorizenet_sdk_python.egg-info/requires.txt
authorizenet_sdk_python.egg-info/top_level.txt