Metadata-Version: 1.1
Name: authorizenet-sdk-python
Version: 1.0.0
Summary: Authorize.Net Python project
Home-page: https://github.com/AuthorizeNet/sdk-python
Author: Authorize.Net Developer
Author-email: developer@authorize.net
License: proprietary
Keywords: authorizenet,authorize.net,payment,ecommerce
Platform: UNKNOWN
Classifier: Development Status :: 4 - Beta
Classifier: Intended Audience :: Developers
Classifier: Topic :: Software Development :: Build Tools
Classifier: License :: Other/Proprietary License
Classifier: Programming Language :: Python :: 2.7
